ontopascii/__init__.py
ontopascii/ontopascii.py
ontopascii/fonts/lucon.ttf
ontopascii-1.0.0.dist-info/LICENSE
ontopascii-1.0.0.dist-info/METADATA
ontopascii-1.0.0.dist-info/WHEEL
ontopascii-1.0.0.dist-info/top_level.txt
ontopascii-1.0.0.dist-info/RECORD
